os2mo_init/__init__.py
os2mo_init/__main__.py
os2mo_init/cli.py
os2mo_init/defaults.py
os2mo_init/initialisers.py
os2mo_init/util.py
os2mo_init-0.0.3.dist-info/LICENSES/MPL-2.0.txt
os2mo_init-0.0.3.dist-info/WHEEL
os2mo_init-0.0.3.dist-info/METADATA
os2mo_init-0.0.3.dist-info/RECORD
