Metadata-Version: 2.1
Name: os2mo-init
Version: 0.0.3
Summary: Database initialiser for OS2mo
Home-page: https://magenta.dk/
License: MPL-2.0
Keywords: os2mo
Author: Magenta
Author-email: info@magenta.dk
Requires-Python: >=3.9,<4.0
Classifier: License :: OSI Approved
Classifier: Programming Language :: Python :: 3
Classifier: Programming Language :: Python :: 3.9
Requires-Dist: click (>=7.1.2,<8.0.0)
Requires-Dist: ra-utils (>=0.4.0,<0.5.0)
Requires-Dist: raclients (>=0.4.3,<0.5.0)
Project-URL: Repository, https://git.magenta.dk/rammearkitektur/os2mo-init
